[
    {
        "id": 1,
        "name": "Brasil",
        "abbr": "BRA",
        "logo": "bra.png"
    },
    {
        "id": 2,
        "name": "Alemanha",
        "abbr": "ALE",
        "logo": "ale.png"
    },
    {
        "id": 3,
        "name": "Arábia Saudita",
        "abbr": "SAU",
        "logo": "sau.png"
    },
    {
        "id": 4,
        "name": "Argentina",
        "abbr": "ARG",
        "logo": "arg.png"
    },
    {
        "id": 5,
        "name": "Austrália",
        "abbr": "AUS",
        "logo": "aus.png"
    },
    {
        "id": 6,
        "name": "Bélgica",
        "abbr": "BEL",
        "logo": "bel.png"
    },
    {
        "id": 7,
        "name": "Camarões",
        "abbr": "CAM",
        "logo": "cam.png"
    },
    {
        "id": 8,
        "name": "Canadá",
        "abbr": "CAN",
        "logo": "can.png"
    },
    {
        "id": 9,
        "name": "Coreia do Sul",
        "abbr": "COR",
        "logo": "cor.png"
    },
    {
        "id": 10,
        "name": "Costa Rica",
        "abbr": "COS",
        "logo": "cos.png"
    },
    {
        "id": 11,
        "name": "Croácia",
        "abbr": "CRO",
        "logo": "cro.png"
    },
    {
        "id": 12,
        "name": "Dinamarca",
        "abbr": "DIN",
        "logo": "din.png"
    },
    {
        "id": 13,
        "name": "Equador",
        "abbr": "EQU",
        "logo": "equ.png"
    },
    {
        "id": 14,
        "name": "Espanha",
        "abbr": "ESP",
        "logo": "esp.png"
    },
    {
        "id": 15,
        "name": "Estados Unidos",
        "abbr": "EUA",
        "logo": "eua.png"
    },
    {
        "id": 16,
        "name": "França",
        "abbr": "FRA",
        "logo": "fra.png"
    },
    {
        "id": 17,
        "name": "Gana",
        "abbr": "GAN",
        "logo": "gan.png"
    },
    {
        "id": 18,
        "name": "Holanda",
        "abbr": "HOL",
        "logo": "hol.png"
    },
    {
        "id": 19,
        "name": "Inglaterra",
        "abbr": "ING",
        "logo": "ing.png"
    },
    {
        "id": 20,
        "name": "Irã",
        "abbr": "IRA",
        "logo": "ira.png"
    },
    {
        "id": 21,
        "name": "Japão",
        "abbr": "JAP",
        "logo": "jap.png"
    },
    {
        "id": 22,
        "name": "Marrocos",
        "abbr": "MAR",
        "logo": "mar.png"
    },
    {
        "id": 23,
        "name": "México",
        "abbr": "MEX",
        "logo": "mex.png"
    },
    {
        "id": 24,
        "name": "País de Gales",
        "abbr": "GAL",
        "logo": "gal.png"
    },
    {
        "id": 25,
        "name": "Polônia",
        "abbr": "POL",
        "logo": "pol.png"
    },
    {
        "id": 26,
        "name": "Portugal",
        "abbr": "POR",
        "logo": "por.png"
    },
    {
        "id": 27,
        "name": "Qatar",
        "abbr": "QAT",
        "logo": "qat.png"
    },
    {
        "id": 28,
        "name": "Senegal",
        "abbr": "SEN",
        "logo": "sen.png"
    },
    {
        "id": 29,
        "name": "Sérvia",
        "abbr": "SRB",
        "logo": "srb.png"
    },
    {
        "id": 30,
        "name": "Suíça",
        "abbr": "SUI",
        "logo": "sui.png"
    },
    {
        "id": 31,
        "name": "Tunísia",
        "abbr": "TUN",
        "logo": "tun.png"
    },
    {
        "id": 32,
        "name": "Uruguai",
        "abbr": "URU",
        "logo": "uru.png"
    }
]